<?xml version="1.0" ?>
<playlist version="1">
  <track>
    <title>05:30 Melbourne City x Adelaide United</title>
    <url>https://w1.sportzsonline.click/channels/hd/hd2.php</url>
  </track>
  <track>
    <title>13:00 Real Madrid U19 x Sporting CP U19</title>
    <url>https://w1.sportzsonline.click/channels/hd/hd4.php</url>
    <url>https://w1.sportzsonline.click/channels/hd/hd10.php</url>
    <url>https://w1.sportzsonline.click/channels/pt/eleven2.php</url>
  </track>
  <track>
    <title>15:00 Internazionale U19 x Benfica U19</title>
    <url>https://w1.sportzsonline.click/channels/hd/hd8.php</url>
    <url>https://w1.sportzsonline.click/channels/pt/eleven3.php</url>
  </track>
  <track>
    <title>15:30 Sporting Braga x Ferencváros</title>
    <url>https://w1.sportzsonline.click/channels/hd/hd1.php</url>
    <url>https://w1.sportzsonline.click/channels/hd/hd4.php</url>
    <url>https://w1.sportzsonline.click/channels/pt/eleven1.php</url>
  </track>
  <track>
    <title>17:00 Eintracht Frankfurt W x Hoffenheim W</title>
    <url>https://w1.sportzsonline.click/channels/hd/hd3.php</url>
  </track>
  <track>
    <title>17:00 Basketball - Champions League: Galatasaray x Rytas Vilnius</title>
    <url>https://w1.sportzsonline.click/channels/pt/sporttv3.php</url>
  </track>
  <track>
    <title>17:45 Barcelona x Newcastle United</title>
    <url>https://w1.sportzsonline.click/channels/hd/hd2.php</url>
    <url>https://w1.sportzsonline.click/channels/hd/hd4.php</url>
    <url>https://w1.sportzsonline.click/channels/hd/hd6.php</url>
    <url>https://w1.sportzsonline.click/channels/hd/hd8.php</url>
    <url>https://w1.sportzsonline.click/channels/hd/hd9.php</url>
    <url>https://w1.sportzsonline.click/channels/pt/eleven1.php</url>
    <url>https://w1.sportzsonline.click/channels/bra/br3.php</url>
  </track>
  <track>
    <title>19:00 Al-Ahli x Al Hilal</title>
    <url>https://w1.sportzsonline.click/channels/pt/sporttv1.php</url>
  </track>
  <track>
    <title>19:00 Al Kholood x Al Ittihad</title>
    <url>https://w1.sportzsonline.click/channels/pt/sporttv2.php</url>
  </track>
  <track>
    <title>19:00 Basketball - Eurocup: Hapoel Jerusalem x Ankara</title>
    <url>https://w1.sportzsonline.click/channels/pt/sporttv3.php</url>
  </track>
  <track>
    <title>20:00 Tottenham Hotspur x Atlético Madrid</title>
    <url>https://w1.sportzsonline.click/channels/hd/hd5.php</url>
    <url>https://w1.sportzsonline.click/channels/hd/hd6.php</url>
    <url>https://w1.sportzsonline.click/channels/hd/hd4.php</url>
    <url>https://w1.sportzsonline.click/channels/pt/eleven1.php</url>
    <url>https://w1.sportzsonline.click/channels/bra/br4.php</url>
  </track>
  <track>
    <title>20:00 Liverpool x Galatasaray</title>
    <url>https://w1.sportzsonline.click/channels/hd/hd1.php</url>
    <url>https://w1.sportzsonline.click/channels/hd/hd8.php</url>
    <url>https://w1.sportzsonline.click/channels/hd/hd10.php</url>
    <url>https://w1.sportzsonline.click/channels/pt/sporttv5.php</url>
    <url>https://w1.sportzsonline.click/channels/bra/br3.php</url>
  </track>
  <track>
    <title>20:00 Bayern München x Atalanta</title>
    <url>https://w1.sportzsonline.click/channels/hd/hd11.php</url>
    <url>https://w1.sportzsonline.click/channels/hd/hd3.php</url>
    <url>https://w1.sportzsonline.click/channels/hd/hd7.php</url>
    <url>https://w1.sportzsonline.click/channels/pt/eleven2.php</url>
    <url>https://w1.sportzsonline.click/channels/bra/br2.php</url>
  </track>
  <track>
    <title>21:00 Padel - Premier Padel: Cancun P2</title>
    <url>https://w1.sportzsonline.click/channels/pt/sporttv3.php</url>
  </track>
  <track>
    <title>22:00 Palmeiras x Botafogo</title>
    <url>https://w1.sportzsonline.click/channels/bra/br1.php</url>
  </track>
  <track>
    <title>22:00 Vila Nova x Confiança</title>
    <url>https://w1.sportzsonline.click/channels/bra/br4.php</url>
  </track>
  <track>
    <title>22:00 Bahia x RB Bragantino</title>
    <url>https://w1.sportzsonline.click/channels/bra/br3.php</url>
  </track>
  <track>
    <title>22:30 Athletico-PR x Cruzeiro</title>
    <url>https://w1.sportzsonline.click/channels/bra/br5.php</url>
  </track>
  <track>
    <title>23:00 NBA: Golden State Warriors @ Boston Celtics</title>
    <url>https://w1.sportzsonline.click/channels/pt/sporttv1.php</url>
  </track>
  <track>
    <title>23:00 Inter Miami x Nashville SC</title>
    <url>https://w1.sportzsonline.click/channels/hd/hd2.php</url>
    <url>https://w1.sportzsonline.click/channels/hd/hd10.php</url>
    <url>https://w1.sportzsonline.click/channels/pt/sporttv2.php</url>
  </track>
  <track>
    <title>23:00 Atlético Mineiro x São Paulo</title>
    <url>https://w1.sportzsonline.click/channels/bra/br2.php</url>
  </track>
  <track>
    <title>23:00 Mirassol x Coritiba</title>
    <url>https://w1.sportzsonline.click/channels/bra/br6.php</url>
  </track>
  <track>
    <title>23:20 Inter Bogotá x Deportivo Pereira</title>
    <url>https://w1.sportzsonline.click/channels/hd/hd11.php</url>
  </track>
  <track>
    <title>00:00 CRB x Figueirense</title>
    <url>https://w1.sportzsonline.click/channels/bra/br4.php</url>
  </track>
  <track>
    <title>00:30 Vasco da Gama x Fluminense</title>
    <url>https://w1.sportzsonline.click/channels/bra/br1.php</url>
  </track>
  <track>
    <title>00:30 Santos x Internacional</title>
    <url>https://w1.sportzsonline.click/channels/bra/br3.php</url>
  </track>
  <track>
    <title>01:00 América x Philadelphia Union</title>
    <url>https://w1.sportzsonline.click/channels/hd/hd2.php</url>
    <url>https://w1.sportzsonline.click/channels/hd/hd10.php</url>
  </track>
  <track>
    <title>01:30 Deportivo Cali x Santa Fe</title>
    <url>https://w1.sportzsonline.click/channels/hd/hd11.php</url>
  </track>
  <track>
    <title>01:30 NBA: Los Angeles Lakers @ Houston Rockets</title>
    <url>https://w1.sportzsonline.click/channels/hd/hd5.php</url>
  </track>
  <track>
    <title>01:30 NHL: Dallas Stars @ Colorado Avalanche</title>
    <url>https://w1.sportzsonline.click/channels/pt/sporttv4.php</url>
  </track>
  <track>
    <title>03:00 Seattle Sounders FC x Vancouver Whitecaps</title>
    <url>https://w1.sportzsonline.click/channels/hd/hd2.php</url>
  </track>
  <track>
    <title>03:00 Toluca x San Diego</title>
    <url>https://w1.sportzsonline.click/channels/hd/hd10.php</url>
  </track>
  <additional>
    <item>HD1 ENGLISH</item>
    <item>HD2 ENGLISH</item>
    <item>HD3 GERMAN</item>
    <item>HD4 FRENCH</item>
    <item>HD5 ENGLISH</item>
    <item>HD6 SPANISH</item>
    <item>HD7 ITALIAN</item>
    <item>HD8 ITALIAN</item>
    <item>HD9 ARABIC</item>
    <item>HD10 ARABIC &amp; SPANISH</item>
    <item>HD11 ENGLISH &amp; SPANISH</item>
    <item>BR1 BRAZILIAN</item>
    <item>BR2 BRAZILIAN</item>
    <item>BR3 BRAZILIAN</item>
    <item>BR4 BRAZILIAN</item>
    <item>BR5 BRAZILIAN</item>
    <item>BR6 BRAZILIAN</item>
  </additional>
</playlist>
