{
  "generated_at": "2026-04-13T02:38:27.589754",
  "total_events": 4,
  "live_events": 4,
  "events": [
    {
      "title": "Toluca vs Atlético San Luis",
      "league": "Liga MX",
      "time": "03:00",
      "timestamp": 1776042000000,
      "logo": "https://iptv.playtorrio.xyz/logo.ico",
      "sources": [
        {
          "name": "TUDN 🇺🇸 USA",
          "channel": "TUDN",
          "country": "🇺🇸 USA",
          "logo": "https://api.cdnlivetv.tv/api/v1/channels/images6318/united-states/tudn.svg",
          "url": "https://cdnlivetv.tv/api/v1/channels/player/?name=tudn&code=us&user=ntvstream&plan=free"
        },
        {
          "name": "TUDN 🇲🇽 Mexico",
          "channel": "TUDN",
          "country": "🇲🇽 Mexico",
          "logo": "https://api.cdnlivetv.tv/api/v1/channels/images6318/mexico/tudn.svg",
          "url": "https://cdnlivetv.tv/api/v1/channels/player/?name=tudn&code=mx&user=ntvstream&plan=free"
        }
      ],
      "live": true
    },
    {
      "title": "Inter Bogotá vs Alianza",
      "league": "Primera A",
      "time": "03:30",
      "timestamp": 1776043800000,
      "logo": "https://iptv.playtorrio.xyz/logo.ico",
      "sources": [
        {
          "name": "Win Futbol 🇨🇴 Colombia",
          "channel": "Win Futbol",
          "country": "🇨🇴 Colombia",
          "logo": "https://api.cdnlivetv.tv/api/v1/channels/images6318/colombia/win-futbol.webp",
          "url": "https://cdnlivetv.tv/api/v1/channels/player/?name=win+futbol&code=co&user=ntvstream&plan=free"
        }
      ],
      "live": true
    },
    {
      "title": "UPNFM vs Real España",
      "league": "Liga Nacional",
      "time": "03:30",
      "timestamp": 1776043800000,
      "logo": "https://iptv.playtorrio.xyz/logo.ico",
      "sources": [
        {
          "name": "FOX Deportes 🇺🇸 USA",
          "channel": "FOX Deportes",
          "country": "🇺🇸 USA",
          "logo": "https://api.cdnlivetv.tv/api/v1/channels/images6318/united-states/fox-deportes.svg",
          "url": "https://cdnlivetv.tv/api/v1/channels/player/?name=fox+deportes&code=us&user=ntvstream&plan=free"
        }
      ],
      "live": true
    },
    {
      "title": "Utah Mammoth vs Calgary Flames",
      "league": "NHL",
      "time": "03:00",
      "timestamp": 1776042000000,
      "logo": "https://iptv.playtorrio.xyz/logo.ico",
      "sources": [
        {
          "name": "Sport 5 Stars 🇮🇱 Israel",
          "channel": "Sport 5 Stars",
          "country": "🇮🇱 Israel",
          "logo": "https://api.cdnlivetv.tv/api/v1/channels/images6318/israel/sport-5-stars.png",
          "url": "https://cdnlivetv.tv/api/v1/channels/player/?name=sport+5+stars&code=il&user=ntvstream&plan=free"
        }
      ],
      "live": true
    }
  ]
}